esl_jupyterlab_codemirror/__init__.py
esl_jupyterlab_codemirror/_version.py
esl_jupyterlab_codemirror/labextension/build_log.json
esl_jupyterlab_codemirror/labextension/package.json
esl_jupyterlab_codemirror/labextension/static/lib_index_js.de30004b223e2e3ba8cf.js
esl_jupyterlab_codemirror/labextension/static/lib_index_js.de30004b223e2e3ba8cf.js.map
esl_jupyterlab_codemirror/labextension/static/remoteEntry.7c9b44409ea17b656663.js
esl_jupyterlab_codemirror/labextension/static/remoteEntry.7c9b44409ea17b656663.js.map
esl_jupyterlab_codemirror/labextension/static/style.js
esl_jupyterlab_codemirror/labextension/static/style_index_js.c8014ed3e0b62f29edc7.js
esl_jupyterlab_codemirror/labextension/static/style_index_js.c8014ed3e0b62f29edc7.js.map
esl_jupyterlab_codemirror/labextension/static/vendors-node_modules_css-loader_dist_runtime_api_js-node_modules_css-loader_dist_runtime_cssW-72eba1.cf702ad9d2145a511462.js
esl_jupyterlab_codemirror/labextension/static/vendors-node_modules_css-loader_dist_runtime_api_js-node_modules_css-loader_dist_runtime_cssW-72eba1.cf702ad9d2145a511462.js.map
esl_jupyterlab_codemirror-0.1.1.data/data/share/jupyter/labextensions/esl-jupyterlab-codemirror/build_log.json
esl_jupyterlab_codemirror-0.1.1.data/data/share/jupyter/labextensions/esl-jupyterlab-codemirror/install.json
esl_jupyterlab_codemirror-0.1.1.data/data/share/jupyter/labextensions/esl-jupyterlab-codemirror/package.json
esl_jupyterlab_codemirror-0.1.1.data/data/share/jupyter/labextensions/esl-jupyterlab-codemirror/static/lib_index_js.de30004b223e2e3ba8cf.js
esl_jupyterlab_codemirror-0.1.1.data/data/share/jupyter/labextensions/esl-jupyterlab-codemirror/static/lib_index_js.de30004b223e2e3ba8cf.js.map
esl_jupyterlab_codemirror-0.1.1.data/data/share/jupyter/labextensions/esl-jupyterlab-codemirror/static/remoteEntry.7c9b44409ea17b656663.js
esl_jupyterlab_codemirror-0.1.1.data/data/share/jupyter/labextensions/esl-jupyterlab-codemirror/static/remoteEntry.7c9b44409ea17b656663.js.map
esl_jupyterlab_codemirror-0.1.1.dist-info/LICENSE
esl_jupyterlab_codemirror-0.1.1.dist-info/METADATA
esl_jupyterlab_codemirror-0.1.1.dist-info/WHEEL
esl_jupyterlab_codemirror-0.1.1.dist-info/top_level.txt
esl_jupyterlab_codemirror-0.1.1.dist-info/RECORD
